browsercontroller/Hardcoded.py
browsercontroller/__init__.py
browsercontroller/__main__.py
browsercontroller/playwright/__init__.py
browsercontroller/playwright/get_driver.py
browsercontroller/playwright/get_driver_with_persistent_context.py
browsercontroller-0.0.13.dist-info/METADATA
browsercontroller-0.0.13.dist-info/WHEEL
browsercontroller-0.0.13.dist-info/entry_points.txt
browsercontroller-0.0.13.dist-info/top_level.txt
browsercontroller-0.0.13.dist-info/RECORD
